LICENSE
MANIFEST.in
README.md
setup.py
python_ravencoinlib.egg-info/PKG-INFO
python_ravencoinlib.egg-info/SOURCES.txt
python_ravencoinlib.egg-info/dependency_links.txt
python_ravencoinlib.egg-info/not-zip-safe
python_ravencoinlib.egg-info/requires.txt
python_ravencoinlib.egg-info/top_level.txt
ravencoin/__init__.py
ravencoin/assets.py
ravencoin/base58.py
ravencoin/bech32.py
ravencoin/bloom.py
ravencoin/messages.py
ravencoin/net.py
ravencoin/rpc.py
ravencoin/segwit_addr.py
ravencoin/signature.py
ravencoin/signmessage.py
ravencoin/wallet.py
ravencoin/blockchain/__init__.py
ravencoin/blockchain/index.py
ravencoin/blockchain/utils.py
ravencoin/core/__init__.py
ravencoin/core/_bignum.py
ravencoin/core/assets.py
ravencoin/core/key.py
ravencoin/core/script.py
ravencoin/core/scripteval.py
ravencoin/core/serialize.py
ravencoin/tests/__init__.py
ravencoin/tests/fakeravencoinproxy.py
ravencoin/tests/test_asset_script.py
ravencoin/tests/test_assets.py
ravencoin/tests/test_base58.py
ravencoin/tests/test_bech32.py
ravencoin/tests/test_bloom.py
ravencoin/tests/test_checkblock.py
ravencoin/tests/test_core.py
ravencoin/tests/test_fakeravencoinproxy.py
ravencoin/tests/test_key.py
ravencoin/tests/test_messages.py
ravencoin/tests/test_messaging.py
ravencoin/tests/test_net.py
ravencoin/tests/test_rpc.py
ravencoin/tests/test_script.py
ravencoin/tests/test_scripteval.py
ravencoin/tests/test_segwit.py
ravencoin/tests/test_serialize.py
ravencoin/tests/test_signmessage.py
ravencoin/tests/test_transactions.py
ravencoin/tests/test_wallet.py
ravencoin/tests/data/base58_encode_decode.json
ravencoin/tests/data/bech32_encode_decode.json
ravencoin/tests/data/bech32_invalid.json
ravencoin/tests/data/checkblock_invalid.json
ravencoin/tests/data/checkblock_valid.json
ravencoin/tests/data/script_invalid.json
ravencoin/tests/data/script_valid.json
ravencoin/tests/data/signmessage.json
ravencoin/tests/data/tx_invalid.json
ravencoin/tests/data/tx_valid.json
version/__init__.py