Metadata-Version: 2.1
Name: python-ravencoinlib
Version: 0.2.2
Summary: Ravencoin fork of python-bitcoinlib
Home-page: https://github.com/standard-error/python-ravencoinlib
Author: standard-error@github
Author-email: ravencoinlib@gmail.com
License: UNKNOWN
Keywords: ravencoin
Platform: UNKNOWN
Classifier: Programming Language :: Python
Classifier: License :: OSI Approved :: GNU Lesser General Public License v3 or later (LGPLv3+)
